LICENSE
MANIFEST.in
README.md
quicktest.py
settings_test.py
setup.py
django_odnoklassniki_discussions.egg-info/PKG-INFO
django_odnoklassniki_discussions.egg-info/SOURCES.txt
django_odnoklassniki_discussions.egg-info/dependency_links.txt
django_odnoklassniki_discussions.egg-info/not-zip-safe
django_odnoklassniki_discussions.egg-info/requires.txt
django_odnoklassniki_discussions.egg-info/top_level.txt
odnoklassniki_discussions/__init__.py
odnoklassniki_discussions/__init__.pyc
odnoklassniki_discussions/admin.py
odnoklassniki_discussions/admin.pyc
odnoklassniki_discussions/factories.py
odnoklassniki_discussions/factories.pyc
odnoklassniki_discussions/models.py
odnoklassniki_discussions/models.pyc
odnoklassniki_discussions/tests.py
odnoklassniki_discussions/tests.pyc
odnoklassniki_discussions/migrations/0001_initial.py
odnoklassniki_discussions/migrations/0001_initial.pyc
odnoklassniki_discussions/migrations/0002_auto__add_field_comment_owner_content_type__add_field_comment_owner_id.py
odnoklassniki_discussions/migrations/0002_auto__add_field_comment_owner_content_type__add_field_comment_owner_id.pyc
odnoklassniki_discussions/migrations/0003_auto__chg_field_discussion_new_comments_count__chg_field_discussion_co.py
odnoklassniki_discussions/migrations/0003_auto__chg_field_discussion_new_comments_count__chg_field_discussion_co.pyc
odnoklassniki_discussions/migrations/0004_auto__del_field_discussion_type__add_field_discussion_object_type__del.py
odnoklassniki_discussions/migrations/0004_auto__del_field_discussion_type__add_field_discussion_object_type__del.pyc
odnoklassniki_discussions/migrations/0005_auto.py
odnoklassniki_discussions/migrations/0005_auto.pyc
odnoklassniki_discussions/migrations/0006_auto__add_field_discussion_reshares_count.py
odnoklassniki_discussions/migrations/0006_auto__add_field_discussion_reshares_count.pyc
odnoklassniki_discussions/migrations/0007_auto__add_index_discussion_date.py
odnoklassniki_discussions/migrations/0007_auto__add_index_discussion_date.pyc
odnoklassniki_discussions/migrations/0008_auto__add_field_discussion_last_vote_date__add_field_discussion_votes_.py
odnoklassniki_discussions/migrations/0008_auto__add_field_discussion_last_vote_date__add_field_discussion_votes_.pyc
odnoklassniki_discussions/migrations/__init__.py
